urm_validatetoken/__init__.py
urm_validatetoken/validatetoken.py
urm_validatetoken-0.0.7.dist-info/METADATA
urm_validatetoken-0.0.7.dist-info/WHEEL
urm_validatetoken-0.0.7.dist-info/top_level.txt
urm_validatetoken-0.0.7.dist-info/RECORD
