Metadata-Version: 2.1
Name: urm-validatetoken
Version: 0.0.7
Summary: urm_validatetoken package contains method validate_token() which takes access_token as input and returns status of the token as valid or invalid.
Author: Shubham Nalawade
Author-email: s.satish.nalawade@accenture.com
Keywords: python,first package
Classifier: Development Status :: 3 - Alpha
Classifier: Intended Audience :: Developers
Classifier: Programming Language :: Python :: 2
Classifier: Programming Language :: Python :: 3
Classifier: Operating System :: MacOS :: MacOS X
Classifier: Operating System :: Microsoft :: Windows
Requires-Dist: urllib3 (>=1.26.12)
Requires-Dist: Flask (>=2.2.2)
